{
  "Default Project": [
    {
      "entry_id": "e1ed99a3-e536-4ed2-8c45-de7e755898ed",
      "name": "nmap",
      "binary_path": "/bin/ls",
      "log_path": "/home/researchdev/Documents/honeygen/pyside-pin-instruction-logger/pin_logs/instruction_log.txt",
      "timestamp": "2025-11-20T09:13:35.085064",
      "sanitized_binary_path": null,
      "parent_entry_id": null,
      "is_sanitized_run": false
    },
    {
      "entry_id": "3be9e700-28ff-4d2a-a356-f3f2924d83a6",
      "name": "run2",
      "binary_path": "/bin/ls",
      "log_path": "/home/researchdev/Documents/honeygen/pyside-pin-instruction-logger/projects/Default_Project/instruction_log.txt",
      "timestamp": "2025-11-20T09:48:59.656853",
      "sanitized_binary_path": null,
      "parent_entry_id": null,
      "is_sanitized_run": false
    },
    {
      "entry_id": "d6b74104-0758-4613-9c60-8294a1f744f2",
      "name": "run3",
      "binary_path": "/bin/ls",
      "log_path": "/home/researchdev/Documents/honeygen/pyside-pin-instruction-logger/projects/Default_Project/instruction_log_run3.txt",
      "timestamp": "2025-11-20T10:15:21.201130",
      "sanitized_binary_path": null,
      "parent_entry_id": null,
      "is_sanitized_run": false
    }
  ],
  "ls_honeypot": [
    {
      "entry_id": "4af6c4ff-6ce5-4fa1-bb3d-c82b40b34db1",
      "name": "ls @ 2025-12-01 18:13:03",
      "binary_path": "/bin/ls",
      "log_path": "/home/researchdev/Documents/honeygen/pyside-pin-instruction-logger/projects/ls_honeypot/instruction_log_ls_2025-12-01_18_13_03.txt",
      "timestamp": "2025-12-01T18:13:16.656410",
      "sanitized_binary_path": null,
      "parent_entry_id": null,
      "is_sanitized_run": false,
      "prepared_segments": [
        {
          "start": 93824993230848,
          "end": 93824993230874
        },
        {
          "start": 93824993231008,
          "end": 93824993231008
        },
        {
          "start": 93824993231104,
          "end": 93824993231130
        },
        {
          "start": 93824993231600,
          "end": 93824993231804
        },
        {
          "start": 93824993231856,
          "end": 93824993231973
        },
        {
          "start": 93824993236517,
          "end": 93824993236636
        },
        {
          "start": 93824993252283,
          "end": 93824993252351
        },
        {
          "start": 93824993255541,
          "end": 93824993255612
        },
        {
          "start": 93824993255689,
          "end": 93824993255760
        },
        {
          "start": 93824993255904,
          "end": 93824993256236
        },
        {
          "start": 93824993260576,
          "end": 93824993260662
        },
        {
          "start": 93824993260773,
          "end": 93824993260895
        },
        {
          "start": 93824993261312,
          "end": 93824993262153
        },
        {
          "start": 93824993262443,
          "end": 93824993262534
        },
        {
          "start": 93824993262575,
          "end": 93824993262681
        },
        {
          "start": 93824993272564,
          "end": 93824993272806
        },
        {
          "start": 93824993273005,
          "end": 93824993273082
        },
        {
          "start": 93824993274082,
          "end": 93824993274139
        },
        {
          "start": 93824993274190,
          "end": 93824993274227
        },
        {
          "start": 93824993274285,
          "end": 93824993274316
        },
        {
          "start": 93824993274452,
          "end": 93824993274477
        },
        {
          "start": 93824993274784,
          "end": 93824993274871
        },
        {
          "start": 93824993295167,
          "end": 93824993295558
        },
        {
          "start": 93824993295597,
          "end": 93824993296073
        },
        {
          "start": 93824993296112,
          "end": 93824993296189
        },
        {
          "start": 93824993296726,
          "end": 93824993296924
        },
        {
          "start": 93824993297515,
          "end": 93824993297648
        },
        {
          "start": 93824993299184,
          "end": 93824993299520
        },
        {
          "start": 93824993446864,
          "end": 93824993446927
        },
        {
          "start": 93824993446997,
          "end": 93824993447018
        },
        {
          "start": 93824993447343,
          "end": 93824993447360
        },
        {
          "start": 93824993450192,
          "end": 93824993450285
        },
        {
          "start": 93824993450413,
          "end": 93824993450554
        },
        {
          "start": 93824993456736,
          "end": 93824993456835
        },
        {
          "start": 93824993456960,
          "end": 93824993457013
        },
        {
          "start": 93824993457065,
          "end": 93824993457261
        },
        {
          "start": 93824993457360,
          "end": 93824993457542
        },
        {
          "start": 93824993457732,
          "end": 93824993457744
        },
        {
          "start": 93824993458420,
          "end": 93824993458439
        },
        {
          "start": 93824993573004,
          "end": 93824993573122
        },
        {
          "start": 93824993574915,
          "end": 93824993575012
        },
        {
          "start": 93824993575706,
          "end": 93824993575765
        },
        {
          "start": 93824993575798,
          "end": 93824993576067
        },
        {
          "start": 93824993577835,
          "end": 93824993577903
        },
        {
          "start": 93824993578131,
          "end": 93824993578172
        },
        {
          "start": 93824993578219,
          "end": 93824993578368
        },
        {
          "start": 93824993578949,
          "end": 93824993579023
        },
        {
          "start": 93824993579112,
          "end": 93824993579187
        },
        {
          "start": 93824993579358,
          "end": 93824993579448
        },
        {
          "start": 93824993580063,
          "end": 93824993580100
        },
        {
          "start": 93824993580168,
          "end": 93824993580191
        },
        {
          "start": 93824993583504,
          "end": 93824993583581
        },
        {
          "start": 93824993583616,
          "end": 93824993583665
        },
        {
          "start": 93824993584649,
          "end": 93824993584672
        },
        {
          "start": 93824993584744,
          "end": 93824993584789
        },
        {
          "start": 93824993584839,
          "end": 93824993584884
        },
        {
          "start": 93824993584943,
          "end": 93824993585003
        },
        {
          "start": 93824993589550,
          "end": 93824993589657
        },
        {
          "start": 93824993591138,
          "end": 93824993591368
        },
        {
          "start": 93824993591440,
          "end": 93824993591557
        },
        {
          "start": 93824993591612,
          "end": 93824993591657
        },
        {
          "start": 93824993591942,
          "end": 93824993591956
        },
        {
          "start": 93824993592018,
          "end": 93824993592146
        },
        {
          "start": 93824993592201,
          "end": 93824993592610
        },
        {
          "start": 93824993628148,
          "end": 93824993628160
        },
        {
          "start": 93824993628498,
          "end": 93824993628561
        },
        {
          "start": 93824993628869,
          "end": 93824993628893
        },
        {
          "start": 93824993629998,
          "end": 93824993630233
        },
        {
          "start": 93824993638713,
          "end": 93824993638729
        },
        {
          "start": 93824993641310,
          "end": 93824993641419
        },
        {
          "start": 93824993644526,
          "end": 93824993644918
        },
        {
          "start": 93824993645134,
          "end": 93824993645358
        },
        {
          "start": 93824993645431,
          "end": 93824993645447
        },
        {
          "start": 93824993645492,
          "end": 93824993645522
        },
        {
          "start": 93824993646205,
          "end": 93824993646250
        },
        {
          "start": 93824993646308,
          "end": 93824993646316
        },
        {
          "start": 93824993646494,
          "end": 93824993646500
        },
        {
          "start": 93824993646543,
          "end": 93824993646570
        },
        {
          "start": 93824993646615,
          "end": 93824993646673
        },
        {
          "start": 93824993646910,
          "end": 93824993646928
        },
        {
          "start": 93824993647322,
          "end": 93824993647342
        },
        {
          "start": 93824993647404,
          "end": 93824993647481
        },
        {
          "start": 93824993647519,
          "end": 93824993647548
        },
        {
          "start": 93824993648154,
          "end": 93824993648265
        },
        {
          "start": 93824993648430,
          "end": 93824993648708
        },
        {
          "start": 93824993649094,
          "end": 93824993649226
        },
        {
          "start": 93824993649550,
          "end": 93824993649571
        },
        {
          "start": 93824993649816,
          "end": 93824993649833
        },
        {
          "start": 93824993651315,
          "end": 93824993651339
        },
        {
          "start": 93824993651375,
          "end": 93824993651387
        },
        {
          "start": 93824993652440,
          "end": 93824993653128
        },
        {
          "start": 93824993655071,
          "end": 93824993655121
        },
        {
          "start": 93824993655239,
          "end": 93824993655317
        },
        {
          "start": 93824993655485,
          "end": 93824993655623
        },
        {
          "start": 93824993655732,
          "end": 93824993655888
        },
        {
          "start": 93824993655988,
          "end": 93824993656083
        },
        {
          "start": 93824993657061,
          "end": 93824993657580
        },
        {
          "start": 93824993658348,
          "end": 93824993658589
        },
        {
          "start": 93824993660287,
          "end": 93824993660328
        },
        {
          "start": 93824993662072,
          "end": 93824993662182
        },
        {
          "start": 93824993662520,
          "end": 93824993662926
        },
        {
          "start": 93824993667485,
          "end": 93824993667640
        },
        {
          "start": 93824993667728,
          "end": 93824993667761
        },
        {
          "start": 93824993670360,
          "end": 93824993670564
        },
        {
          "start": 93824993671567,
          "end": 93824993671607
        },
        {
          "start": 93824993673572,
          "end": 93824993673832
        },
        {
          "start": 93824993675374,
          "end": 93824993675430
        },
        {
          "start": 93824993675473,
          "end": 93824993675489
        },
        {
          "start": 93824993678279,
          "end": 93824993678452
        },
        {
          "start": 93824993678675,
          "end": 93824993678720
        },
        {
          "start": 93824993679099,
          "end": 93824993679124
        },
        {
          "start": 93824993680163,
          "end": 93824993680470
        },
        {
          "start": 93824993680662,
          "end": 93824993680722
        },
        {
          "start": 93824993680843,
          "end": 93824993680912
        },
        {
          "start": 93824993683487,
          "end": 93824993683523
        },
        {
          "start": 93824993683605,
          "end": 93824993683642
        },
        {
          "start": 93824993684246,
          "end": 93824993684362
        },
        {
          "start": 93824993684487,
          "end": 93824993684982
        },
        {
          "start": 93824993685022,
          "end": 93824993685049
        },
        {
          "start": 93824993685173,
          "end": 93824993685175
        },
        {
          "start": 93824993685233,
          "end": 93824993685267
        },
        {
          "start": 93824993685339,
          "end": 93824993685853
        },
        {
          "start": 93824993685953,
          "end": 93824993685961
        },
        {
          "start": 93824993685997,
          "end": 93824993686101
        },
        {
          "start": 93824993686589,
          "end": 93824993686615
        },
        {
          "start": 93824993686698,
          "end": 93824993686919
        },
        {
          "start": 93824993687417,
          "end": 93824993687572
        },
        {
          "start": 93824993687612,
          "end": 93824993687633
        },
        {
          "start": 93824993687675,
          "end": 93824993687719
        },
        {
          "start": 93824993687832,
          "end": 93824993687842
        },
        {
          "start": 93824993687922,
          "end": 93824993688017
        },
        {
          "start": 93824993688372,
          "end": 93824993688378
        },
        {
          "start": 93824993688576,
          "end": 93824993688729
        },
        {
          "start": 93824993688777,
          "end": 93824993688833
        },
        {
          "start": 93824993688886,
          "end": 93824993688906
        },
        {
          "start": 93824993690786,
          "end": 93824993690802
        },
        {
          "start": 93824993690918,
          "end": 93824993690966
        },
        {
          "start": 93824993691004,
          "end": 93824993691067
        },
        {
          "start": 93824993691115,
          "end": 93824993691128
        },
        {
          "start": 93824993693094,
          "end": 93824993693132
        },
        {
          "start": 93824993693508,
          "end": 93824993694140
        },
        {
          "start": 93824993694298,
          "end": 93824993694787
        },
        {
          "start": 93824993697565,
          "end": 93824993697684
        },
        {
          "start": 93824993697835,
          "end": 93824993697846
        },
        {
          "start": 93824993698059,
          "end": 93824993698138
        },
        {
          "start": 93824993698190,
          "end": 93824993698265
        },
        {
          "start": 93824993698329,
          "end": 93824993698499
        },
        {
          "start": 93824993698736,
          "end": 93824993698850
        },
        {
          "start": 93824993699057,
          "end": 93824993699092
        },
        {
          "start": 93824993699206,
          "end": 93824993699242
        },
        {
          "start": 93824993699512,
          "end": 93824993699594
        },
        {
          "start": 93824993699960,
          "end": 93824993700055
        },
        {
          "start": 93824993700152,
          "end": 93824993700231
        },
        {
          "start": 93824993703214,
          "end": 93824993703297
        },
        {
          "start": 93824993703362,
          "end": 93824993703670
        },
        {
          "start": 93824993703883,
          "end": 93824993703934
        },
        {
          "start": 93824993704316,
          "end": 93824993704689
        },
        {
          "start": 93824993705074,
          "end": 93824993705390
        },
        {
          "start": 93824993713162,
          "end": 93824993713245
        },
        {
          "start": 93824993714046,
          "end": 93824993714129
        },
        {
          "start": 93824993714475,
          "end": 93824993714753
        },
        {
          "start": 93824993714796,
          "end": 93824993714900
        },
        {
          "start": 93824993724561,
          "end": 93824993724586
        },
        {
          "start": 93824993724680,
          "end": 93824993724828
        },
        {
          "start": 93824993725388,
          "end": 93824993725405
        },
        {
          "start": 93824993725779,
          "end": 93824993725879
        },
        {
          "start": 93824993726056,
          "end": 93824993726090
        },
        {
          "start": 93824993726165,
          "end": 93824993726255
        },
        {
          "start": 93824993726303,
          "end": 93824993726539
        },
        {
          "start": 93824993726739,
          "end": 93824993726961
        },
        {
          "start": 93824993727131,
          "end": 93824993727211
        },
        {
          "start": 93824993727271,
          "end": 93824993727280
        },
        {
          "start": 93824993727795,
          "end": 93824993727950
        },
        {
          "start": 93824993728308,
          "end": 93824993728403
        },
        {
          "start": 93824993728457,
          "end": 93824993728471
        },
        {
          "start": 93824993728632,
          "end": 93824993728866
        },
        {
          "start": 93824993728935,
          "end": 93824993729128
        },
        {
          "start": 93824993729226,
          "end": 93824993729488
        },
        {
          "start": 93824993729716,
          "end": 93824993729956
        },
        {
          "start": 93824993730010,
          "end": 93824993730018
        },
        {
          "start": 93824993730129,
          "end": 93824993730221
        },
        {
          "start": 93824993743682,
          "end": 93824993743728
        },
        {
          "start": 93824993745494,
          "end": 93824993745559
        },
        {
          "start": 93824993745650,
          "end": 93824993745727
        },
        {
          "start": 93824993746509,
          "end": 93824993746587
        },
        {
          "start": 93824993746621,
          "end": 93824993746704
        },
        {
          "start": 93824993749118,
          "end": 93824993749200
        },
        {
          "start": 93824993749403,
          "end": 93824993749457
        },
        {
          "start": 93824993751379,
          "end": 93824993751386
        },
        {
          "start": 93824993757433,
          "end": 93824993757458
        },
        {
          "start": 93824993757969,
          "end": 93824993757994
        },
        {
          "start": 93824993758943,
          "end": 93824993758950
        },
        {
          "start": 93824993760584,
          "end": 93824993760780
        },
        {
          "start": 93824993761383,
          "end": 93824993761454
        },
        {
          "start": 93824993761818,
          "end": 93824993761843
        },
        {
          "start": 93824993765080,
          "end": 93824993765200
        },
        {
          "start": 93824993765390,
          "end": 93824993765407
        },
        {
          "start": 93824993839257,
          "end": 93824993839297
        },
        {
          "start": 93824993839579,
          "end": 93824993839630
        },
        {
          "start": 93824993839952,
          "end": 93824993839975
        },
        {
          "start": 93824993840104,
          "end": 93824993840214
        },
        {
          "start": 93824993840967,
          "end": 93824993841023
        },
        {
          "start": 93824993875824,
          "end": 93824993875888
        },
        {
          "start": 93824993876156,
          "end": 93824993876333
        },
        {
          "start": 93824993877792,
          "end": 93824993877828
        },
        {
          "start": 93824993878720,
          "end": 93824993878755
        },
        {
          "start": 93824993907008,
          "end": 93824993907037
        },
        {
          "start": 93824993907083,
          "end": 93824993907337
        },
        {
          "start": 93824993907459,
          "end": 93824993907479
        },
        {
          "start": 93824993910928,
          "end": 93824993911102
        },
        {
          "start": 93824993911399,
          "end": 93824993911447
        },
        {
          "start": 93824993927568,
          "end": 93824993927643
        },
        {
          "start": 93824993927953,
          "end": 93824993927992
        },
        {
          "start": 93824993936976,
          "end": 93824993937119
        },
        {
          "start": 93824993937159,
          "end": 93824993937238
        },
        {
          "start": 93824993944960,
          "end": 93824993945128
        },
        {
          "start": 93824993945181,
          "end": 93824993945268
        },
        {
          "start": 93824993945312,
          "end": 93824993945413
        },
        {
          "start": 93824993945936,
          "end": 93824993945998
        },
        {
          "start": 93824993946120,
          "end": 93824993946204
        },
        {
          "start": 93824993955620,
          "end": 93824993955671
        },
        {
          "start": 93824993956267,
          "end": 93824993956281
        },
        {
          "start": 93824993961714,
          "end": 93824993961752
        },
        {
          "start": 93824993966313,
          "end": 93824993966372
        },
        {
          "start": 93824993974565,
          "end": 93824993975174
        },
        {
          "start": 93824993975548,
          "end": 93824993975714
        },
        {
          "start": 93824993975813,
          "end": 93824993975950
        },
        {
          "start": 93824993975996,
          "end": 93824993976117
        },
        {
          "start": 93824993976198,
          "end": 93824993976285
        },
        {
          "start": 93824993979424,
          "end": 93824993979451
        },
        {
          "start": 93824993980206,
          "end": 93824993980288
        },
        {
          "start": 93824994062384,
          "end": 93824994062388
        },
        {
          "start": 93824994096964,
          "end": 93824994097003
        },
        {
          "start": 93824994122142,
          "end": 93824994122202
        },
        {
          "start": 93824994122238,
          "end": 93824994122257
        },
        {
          "start": 93824994124439,
          "end": 93824994124499
        },
        {
          "start": 93824994129993,
          "end": 93824994130192
        },
        {
          "start": 93824994163113,
          "end": 93824994163220
        },
        {
          "start": 93824994187203,
          "end": 93824994187239
        },
        {
          "start": 93824994187286,
          "end": 93824994187330
        },
        {
          "start": 93824994287391,
          "end": 93824994287439
        },
        {
          "start": 93824994287625,
          "end": 93824994287813
        },
        {
          "start": 93824994290530,
          "end": 93824994290581
        },
        {
          "start": 93824994291170,
          "end": 93824994291194
        },
        {
          "start": 93824994291680,
          "end": 93824994291964
        },
        {
          "start": 93824994292008,
          "end": 93824994292050
        },
        {
          "start": 93824994292190,
          "end": 93824994292204
        },
        {
          "start": 93824994292283,
          "end": 93824994292328
        },
        {
          "start": 93824994292361,
          "end": 93824994292365
        },
        {
          "start": 93824994293562,
          "end": 93824994293570
        },
        {
          "start": 93824994293611,
          "end": 93824994293719
        },
        {
          "start": 93824994294377,
          "end": 93824994294697
        },
        {
          "start": 93824994294755,
          "end": 93824994294851
        },
        {
          "start": 93824994294919,
          "end": 93824994294955
        },
        {
          "start": 93824994295333,
          "end": 93824994295358
        },
        {
          "start": 93824994314884,
          "end": 93824994314911
        },
        {
          "start": 93824994315017,
          "end": 93824994315034
        },
        {
          "start": 93824994315487,
          "end": 93824994315547
        },
        {
          "start": 93824994318475,
          "end": 93824994318528
        },
        {
          "start": 93824994321839,
          "end": 93824994321870
        },
        {
          "start": 93824994363128,
          "end": 93824994363290
        },
        {
          "start": 93824994363327,
          "end": 93824994363698
        },
        {
          "start": 93824994364811,
          "end": 93824994364836
        },
        {
          "start": 93824994374596,
          "end": 93824994374859
        },
        {
          "start": 93824994484618,
          "end": 93824994484787
        },
        {
          "start": 93824994485003,
          "end": 93824994485027
        },
        {
          "start": 93824994485079,
          "end": 93824994485122
        },
        {
          "start": 93824994486749,
          "end": 93824994486803
        },
        {
          "start": 93824994486997,
          "end": 93824994487003
        },
        {
          "start": 93824994487066,
          "end": 93824994487074
        },
        {
          "start": 93824994487164,
          "end": 93824994487167
        },
        {
          "start": 93824994487774,
          "end": 93824994487843
        },
        {
          "start": 93824994488273,
          "end": 93824994488293
        },
        {
          "start": 93824994488348,
          "end": 93824994488351
        },
        {
          "start": 93824994488886,
          "end": 93824994489217
        },
        {
          "start": 93824994489353,
          "end": 93824994489373
        },
        {
          "start": 93824994490556,
          "end": 93824994490794
        },
        {
          "start": 93824994490892,
          "end": 93824994491022
        },
        {
          "start": 93824994491166,
          "end": 93824994491294
        },
        {
          "start": 93824994491374,
          "end": 93824994491396
        },
        {
          "start": 93824994491807,
          "end": 93824994491919
        },
        {
          "start": 93824994492554,
          "end": 93824994492617
        },
        {
          "start": 93824994492667,
          "end": 93824994492758
        },
        {
          "start": 93824994492941,
          "end": 93824994492981
        },
        {
          "start": 93824994493023,
          "end": 93824994493156
        },
        {
          "start": 93824994493338,
          "end": 93824994493368
        },
        {
          "start": 93824994493732,
          "end": 93824994493877
        },
        {
          "start": 93824994493951,
          "end": 93824994494896
        },
        {
          "start": 93824994495015,
          "end": 93824994495178
        },
        {
          "start": 93824994495245,
          "end": 93824994495284
        },
        {
          "start": 93824994495332,
          "end": 93824994495408
        },
        {
          "start": 93824994495468,
          "end": 93824994495654
        },
        {
          "start": 93824994495851,
          "end": 93824994495888
        },
        {
          "start": 93824994495988,
          "end": 93824994496111
        },
        {
          "start": 93824994496183,
          "end": 93824994496329
        },
        {
          "start": 93824994496952,
          "end": 93824994497095
        },
        {
          "start": 93824994497163,
          "end": 93824994497223
        },
        {
          "start": 93824994497290,
          "end": 93824994497906
        },
        {
          "start": 93824994498164,
          "end": 93824994498324
        },
        {
          "start": 93824994499304,
          "end": 93824994499363
        },
        {
          "start": 93824994499453,
          "end": 93824994499511
        },
        {
          "start": 93824994499571,
          "end": 93824994499613
        },
        {
          "start": 93824994502605,
          "end": 93824994502824
        },
        {
          "start": 93824994502905,
          "end": 93824994503008
        },
        {
          "start": 93824994503117,
          "end": 93824994503209
        },
        {
          "start": 93824994504106,
          "end": 93824994504155
        },
        {
          "start": 93824994504236,
          "end": 93824994504285
        },
        {
          "start": 93824994504719,
          "end": 93824994504744
        },
        {
          "start": 93824994504781,
          "end": 93824994504861
        },
        {
          "start": 93824994504929,
          "end": 93824994504954
        },
        {
          "start": 93824994505072,
          "end": 93824994505194
        },
        {
          "start": 93824994505241,
          "end": 93824994505263
        },
        {
          "start": 93824994505687,
          "end": 93824994505770
        },
        {
          "start": 93824994506700,
          "end": 93824994506809
        },
        {
          "start": 93824994507266,
          "end": 93824994507326
        },
        {
          "start": 93824994508994,
          "end": 93824994509025
        },
        {
          "start": 93824994509386,
          "end": 93824994509451
        },
        {
          "start": 93824994510362,
          "end": 93824994510389
        },
        {
          "start": 93824994510476,
          "end": 93824994510729
        },
        {
          "start": 93824994511168,
          "end": 93824994511236
        },
        {
          "start": 93824994519565,
          "end": 93824994520031
        },
        {
          "start": 93824994520731,
          "end": 93824994520764
        },
        {
          "start": 93824994525501,
          "end": 93824994525541
        },
        {
          "start": 93824994525574,
          "end": 93824994525588
        },
        {
          "start": 93824994526137,
          "end": 93824994526162
        },
        {
          "start": 93824994590227,
          "end": 93824994590342
        },
        {
          "start": 93824994590453,
          "end": 93824994590785
        },
        {
          "start": 93824994592438,
          "end": 93824994592514
        },
        {
          "start": 93824994592567,
          "end": 93824994592686
        },
        {
          "start": 93824994593022,
          "end": 93824994593154
        },
        {
          "start": 93824994593950,
          "end": 93824994593977
        },
        {
          "start": 93824994594185,
          "end": 93824994594200
        },
        {
          "start": 93824994596470,
          "end": 93824994596612
        },
        {
          "start": 93824994598025,
          "end": 93824994598045
        },
        {
          "start": 93824994598173,
          "end": 93824994598183
        },
        {
          "start": 93824994602773,
          "end": 93824994602799
        },
        {
          "start": 93824994602841,
          "end": 93824994603695
        },
        {
          "start": 93824994606018,
          "end": 93824994606220
        },
        {
          "start": 93824994606309,
          "end": 93824994606358
        },
        {
          "start": 93824994606565,
          "end": 93824994606801
        },
        {
          "start": 93824994800248,
          "end": 93824994800329
        },
        {
          "start": 93824994800986,
          "end": 93824994801198
        },
        {
          "start": 93824994822549,
          "end": 93824994822643
        },
        {
          "start": 93824994824614,
          "end": 93824994824656
        },
        {
          "start": 93824994829835,
          "end": 93824994829874
        },
        {
          "start": 93824994832044,
          "end": 93824994832344
        },
        {
          "start": 93824994832495,
          "end": 93824994832838
        },
        {
          "start": 93824994832964,
          "end": 93824994833037
        },
        {
          "start": 93824994834818,
          "end": 93824994834885
        },
        {
          "start": 93824994835401,
          "end": 93824994835494
        },
        {
          "start": 93824994841928,
          "end": 93824994841944
        },
        {
          "start": 93824994844096,
          "end": 93824994844139
        },
        {
          "start": 93824994860129,
          "end": 93824994860163
        },
        {
          "start": 93824994860205,
          "end": 93824994860298
        },
        {
          "start": 93824994976906,
          "end": 93824994976963
        },
        {
          "start": 93824994977046,
          "end": 93824994977074
        },
        {
          "start": 93824994977236,
          "end": 93824994977237
        },
        {
          "start": 93824995286510,
          "end": 93824995286645
        },
        {
          "start": 93824995286914,
          "end": 93824995287060
        },
        {
          "start": 93824995287920,
          "end": 93824995287967
        },
        {
          "start": 93824995288991,
          "end": 93824995289523
        },
        {
          "start": 93824995292079,
          "end": 93824995292160
        },
        {
          "start": 93824995293222,
          "end": 93824995293345
        },
        {
          "start": 93824995293387,
          "end": 93824995293404
        },
        {
          "start": 93824995344092,
          "end": 93824995344134
        },
        {
          "start": 93824995442084,
          "end": 93824995442144
        },
        {
          "start": 93824995442483,
          "end": 93824995442578
        },
        {
          "start": 93824995513167,
          "end": 93824995513253
        },
        {
          "start": 93824995513415,
          "end": 93824995513416
        },
        {
          "start": 93824995556749,
          "end": 93824995556774
        },
        {
          "start": 93824995635920,
          "end": 93824995636121
        },
        {
          "start": 93824995636594,
          "end": 93824995636614
        },
        {
          "start": 93824995640240,
          "end": 93824995640401
        },
        {
          "start": 93824995640512,
          "end": 93824995640560
        },
        {
          "start": 93824995640604,
          "end": 93824995640745
        },
        {
          "start": 93824995643168,
          "end": 93824995643262
        },
        {
          "start": 93824995643648,
          "end": 93824995643741
        },
        {
          "start": 93824995644144,
          "end": 93824995644276
        },
        {
          "start": 93824995644326,
          "end": 93824995644343
        },
        {
          "start": 93824995645194,
          "end": 93824995645211
        },
        {
          "start": 93824995645520,
          "end": 93824995645567
        },
        {
          "start": 93824995658736,
          "end": 93824995658793
        },
        {
          "start": 93824995660256,
          "end": 93824995660433
        },
        {
          "start": 93824995689984,
          "end": 93824995690115
        },
        {
          "start": 93824995699568,
          "end": 93824995699729
        },
        {
          "start": 93824995699778,
          "end": 93824995699792
        },
        {
          "start": 93824995700064,
          "end": 93824995700250
        },
        {
          "start": 93824995703136,
          "end": 93824995703158
        },
        {
          "start": 93824995726608,
          "end": 93824995726664
        },
        {
          "start": 93824995726736,
          "end": 93824995726819
        },
        {
          "start": 93824995726962,
          "end": 93824995727080
        },
        {
          "start": 93824995729952,
          "end": 93824995730303
        },
        {
          "start": 93824995730350,
          "end": 93824995730402
        },
        {
          "start": 93824995799280,
          "end": 93824995799311
        },
        {
          "start": 93824995802000,
          "end": 93824995802021
        },
        {
          "start": 93824995802077,
          "end": 93824995802079
        },
        {
          "start": 93824995802253,
          "end": 93824995802267
        },
        {
          "start": 93824995802352,
          "end": 93824995802465
        },
        {
          "start": 93824995802976,
          "end": 93824995803007
        },
        {
          "start": 93824995803071,
          "end": 93824995803079
        },
        {
          "start": 93824995807104,
          "end": 93824995807462
        },
        {
          "start": 93824995807920,
          "end": 93824995807953
        },
        {
          "start": 93824995807997,
          "end": 93824995808031
        },
        {
          "start": 93824995808073,
          "end": 93824995808256
        },
        {
          "start": 93824995808400,
          "end": 93824995808780
        },
        {
          "start": 93824995810256,
          "end": 93824995810528
        },
        {
          "start": 93824995810605,
          "end": 93824995810645
        },
        {
          "start": 93824995810742,
          "end": 93824995810794
        },
        {
          "start": 93824995811984,
          "end": 93824995812125
        },
        {
          "start": 93824995812236,
          "end": 93824995812273
        },
        {
          "start": 93824995813104,
          "end": 93824995813230
        },
        {
          "start": 93824995813291,
          "end": 93824995813357
        },
        {
          "start": 93824995813390,
          "end": 93824995813445
        },
        {
          "start": 93824995815680,
          "end": 93824995815760
        },
        {
          "start": 93824995815961,
          "end": 93824995815965
        },
        {
          "start": 93824995815998,
          "end": 93824995816002
        },
        {
          "start": 93824995816035,
          "end": 93824995816175
        },
        {
          "start": 93824995816352,
          "end": 93824995816869
        },
        {
          "start": 93824995816906,
          "end": 93824995816992
        },
        {
          "start": 93824995817027,
          "end": 93824995817045
        },
        {
          "start": 93824995844896,
          "end": 93824995845156
        },
        {
          "start": 93824995847168,
          "end": 93824995847302
        },
        {
          "start": 93824995850944,
          "end": 93824995851063
        },
        {
          "start": 93824995861104,
          "end": 93824995861147
        },
        {
          "start": 93824995864000,
          "end": 93824995864100
        },
        {
          "start": 93824995864141,
          "end": 93824995864361
        },
        {
          "start": 93824995864544,
          "end": 93824995864571
        },
        {
          "start": 93824995864736,
          "end": 93824995864771
        },
        {
          "start": 93824995864813,
          "end": 93824995864934
        },
        {
          "start": 93824995870992,
          "end": 93824995871010
        },
        {
          "start": 93824995871064,
          "end": 93824995871121
        },
        {
          "start": 93824995871187,
          "end": 93824995871202
        },
        {
          "start": 93824995872128,
          "end": 93824995872214
        },
        {
          "start": 93824995872280,
          "end": 93824995872333
        },
        {
          "start": 93824995887440,
          "end": 93824995887447
        },
        {
          "start": 93824995887728,
          "end": 93824995887764
        },
        {
          "start": 93824995905200,
          "end": 93824995905301
        },
        {
          "start": 93824995905357,
          "end": 93824995905387
        },
        {
          "start": 93824995905459,
          "end": 93824995905488
        },
        {
          "start": 93824995906432,
          "end": 93824995906667
        },
        {
          "start": 93824995908544,
          "end": 93824995908559
        },
        {
          "start": 93824995909680,
          "end": 93824995910225
        },
        {
          "start": 93824995910320,
          "end": 93824995910350
        },
        {
          "start": 93824995910582,
          "end": 93824995910767
        },
        {
          "start": 93824995913888,
          "end": 93824995914141
        },
        {
          "start": 93824995914208,
          "end": 93824995914399
        },
        {
          "start": 93824995914656,
          "end": 93824995914845
        },
        {
          "start": 93824995914976,
          "end": 93824995915010
        },
        {
          "start": 93824995915045,
          "end": 93824995915121
        },
        {
          "start": 93824995915300,
          "end": 93824995915346
        },
        {
          "start": 93824995915432,
          "end": 93824995915487
        },
        {
          "start": 93824995915632,
          "end": 93824995915733
        },
        {
          "start": 93824995915784,
          "end": 93824995915807
        },
        {
          "start": 93824995915872,
          "end": 93824995916073
        },
        {
          "start": 93824995917328,
          "end": 93824995917776
        },
        {
          "start": 93824995920704,
          "end": 93824995920919
        },
        {
          "start": 93824995922672,
          "end": 93824995922867
        },
        {
          "start": 93824995923056,
          "end": 93824995923391
        },
        {
          "start": 93824995927408,
          "end": 93824995927423
        },
        {
          "start": 93824995931744,
          "end": 93824995931791
        },
        {
          "start": 93824995934368,
          "end": 93824995934385
        },
        {
          "start": 93824995936356,
          "end": 93824995936374
        },
        {
          "start": 93824995941192,
          "end": 93824995941711
        },
        {
          "start": 93824995975209,
          "end": 93824995975234
        },
        {
          "start": 93824995976044,
          "end": 93824995976434
        },
        {
          "start": 93824995979031,
          "end": 93824995979145
        },
        {
          "start": 93824995979190,
          "end": 93824995979219
        },
        {
          "start": 93824995979408,
          "end": 93824995979472
        },
        {
          "start": 93824995979633,
          "end": 93824995979907
        },
        {
          "start": 93824995980026,
          "end": 93824995980225
        },
        {
          "start": 93824995982295,
          "end": 93824995982664
        },
        {
          "start": 93824995982808,
          "end": 93824995983002
        },
        {
          "start": 93824995983066,
          "end": 93824995983306
        },
        {
          "start": 93824995983343,
          "end": 93824995983431
        },
        {
          "start": 93824995983492,
          "end": 93824995983523
        },
        {
          "start": 93824995983597,
          "end": 93824995983688
        },
        {
          "start": 93824995983798,
          "end": 93824995983867
        },
        {
          "start": 93824995983911,
          "end": 93824995984333
        },
        {
          "start": 93824995984384,
          "end": 93824995984455
        },
        {
          "start": 93824995992071,
          "end": 93824995992140
        },
        {
          "start": 93824995997965,
          "end": 93824995997999
        },
        {
          "start": 93824995998089,
          "end": 93824995998095
        },
        {
          "start": 93824995998132,
          "end": 93824995998145
        },
        {
          "start": 93824995998251,
          "end": 93824995998321
        },
        {
          "start": 93824996723024,
          "end": 93824996723141
        },
        {
          "start": 93824996723198,
          "end": 93824996723222
        },
        {
          "start": 93824996723313,
          "end": 93824996723837
        },
        {
          "start": 93824996723887,
          "end": 93824996723947
        },
        {
          "start": 93824996724022,
          "end": 93824996724035
        },
        {
          "start": 93824996724167,
          "end": 93824996724218
        },
        {
          "start": 93824996726615,
          "end": 93824996726649
        },
        {
          "start": 93824996726698,
          "end": 93824996726719
        },
        {
          "start": 93824996726912,
          "end": 93824996727004
        },
        {
          "start": 93824996727121,
          "end": 93824996727223
        },
        {
          "start": 93824996727331,
          "end": 93824996727421
        },
        {
          "start": 93824996728769,
          "end": 93824996728773
        },
        {
          "start": 93824996728808,
          "end": 93824996728810
        },
        {
          "start": 93824996728952,
          "end": 93824996729079
        },
        {
          "start": 93824996729349,
          "end": 93824996729380
        },
        {
          "start": 93824996729663,
          "end": 93824996729742
        },
        {
          "start": 93824996729894,
          "end": 93824996729954
        },
        {
          "start": 93824996730114,
          "end": 93824996730180
        },
        {
          "start": 93824996731040,
          "end": 93824996731136
        },
        {
          "start": 93824996731212,
          "end": 93824996731270
        },
        {
          "start": 93824996731309,
          "end": 93824996731333
        },
        {
          "start": 93824996731414,
          "end": 93824996731497
        },
        {
          "start": 93824996731642,
          "end": 93824996731851
        },
        {
          "start": 93824996731932,
          "end": 93824996731955
        },
        {
          "start": 93824996731989,
          "end": 93824996732077
        },
        {
          "start": 93824996732142,
          "end": 93824996732170
        },
        {
          "start": 93824996732214,
          "end": 93824996732235
        },
        {
          "start": 93824996732495,
          "end": 93824996733019
        },
        {
          "start": 93824996733291,
          "end": 93824996733584
        },
        {
          "start": 93824996733639,
          "end": 93824996733664
        },
        {
          "start": 93824996733752,
          "end": 93824996733922
        },
        {
          "start": 93824996733973,
          "end": 93824996734046
        },
        {
          "start": 93824996734081,
          "end": 93824996734299
        },
        {
          "start": 93824996734344,
          "end": 93824996734369
        },
        {
          "start": 93824996734470,
          "end": 93824996734545
        },
        {
          "start": 93824996734772,
          "end": 93824996734942
        },
        {
          "start": 93824996735128,
          "end": 93824996735200
        },
        {
          "start": 93824996735672,
          "end": 93824996735745
        },
        {
          "start": 93824996736013,
          "end": 93824996736125
        },
        {
          "start": 93824996736171,
          "end": 93824996736393
        },
        {
          "start": 93824996736468,
          "end": 93824996736492
        },
        {
          "start": 93824996736550,
          "end": 93824996736553
        },
        {
          "start": 93824996736811,
          "end": 93824996736846
        },
        {
          "start": 93824996736980,
          "end": 93824996737002
        },
        {
          "start": 93824996737100,
          "end": 93824996737139
        },
        {
          "start": 93824996737226,
          "end": 93824996737240
        },
        {
          "start": 93824996737672,
          "end": 93824996737724
        },
        {
          "start": 93824996738255,
          "end": 93824996738345
        },
        {
          "start": 93824996738549,
          "end": 93824996738673
        },
        {
          "start": 93824996739338,
          "end": 93824996739468
        },
        {
          "start": 93824996740112,
          "end": 93824996740900
        },
        {
          "start": 93824996740948,
          "end": 93824996740965
        },
        {
          "start": 93824996741017,
          "end": 93824996741021
        },
        {
          "start": 93824996741331,
          "end": 93824996741675
        },
        {
          "start": 93824996741752,
          "end": 93824996742465
        },
        {
          "start": 93824996744441,
          "end": 93824996760072
        },
        {
          "start": 93824996760114,
          "end": 93824996760377
        },
        {
          "start": 93824996760424,
          "end": 93824996760451
        },
        {
          "start": 93824996760523,
          "end": 93824996760740
        },
        {
          "start": 93824996760977,
          "end": 93824996761142
        },
        {
          "start": 93824996761330,
          "end": 93824996761428
        },
        {
          "start": 93824996761663,
          "end": 93824996762251
        },
        {
          "start": 93824996762303,
          "end": 93824996762396
        },
        {
          "start": 93824996762533,
          "end": 93824996762569
        },
        {
          "start": 93824996762625,
          "end": 93824996762743
        },
        {
          "start": 93824996763051,
          "end": 93824996763080
        },
        {
          "start": 93824996763275,
          "end": 93824996763473
        },
        {
          "start": 93824996763695,
          "end": 93824996763699
        },
        {
          "start": 93824996763746,
          "end": 93824996763797
        },
        {
          "start": 93824996763906,
          "end": 93824996764012
        },
        {
          "start": 93824996764269,
          "end": 93824996764277
        },
        {
          "start": 93824996764490,
          "end": 93824996764533
        },
        {
          "start": 93824996764596,
          "end": 93824996764602
        },
        {
          "start": 93824996764804,
          "end": 93824996764858
        },
        {
          "start": 93824996765118,
          "end": 93824996765402
        },
        {
          "start": 93824996765612,
          "end": 93824996765713
        },
        {
          "start": 93824996765758,
          "end": 93824996765772
        },
        {
          "start": 93824996765832,
          "end": 93824996766080
        },
        {
          "start": 93824996766920,
          "end": 93824996767004
        },
        {
          "start": 93824996768327,
          "end": 93824996768342
        },
        {
          "start": 93824996768425,
          "end": 93824996768461
        },
        {
          "start": 93824996768614,
          "end": 93824996768671
        },
        {
          "start": 93824996768896,
          "end": 93824996768904
        },
        {
          "start": 93824996769228,
          "end": 93824996769263
        },
        {
          "start": 93824996769324,
          "end": 93824996769546
        },
        {
          "start": 93824996772642,
          "end": 93824996772666
        },
        {
          "start": 93824996772719,
          "end": 93824996772784
        },
        {
          "start": 93824996772929,
          "end": 93824996773303
        },
        {
          "start": 93824996773667,
          "end": 93824996773930
        },
        {
          "start": 93824996774493,
          "end": 93824996774515
        },
        {
          "start": 93824996776283,
          "end": 93824996776409
        },
        {
          "start": 93824996776470,
          "end": 93824996776483
        },
        {
          "start": 93824996776555,
          "end": 93824996776580
        },
        {
          "start": 93824996776646,
          "end": 93824996776660
        },
        {
          "start": 93824996776854,
          "end": 93824996776864
        },
        {
          "start": 93824996777738,
          "end": 93824996777752
        },
        {
          "start": 93824996777938,
          "end": 93824996778043
        },
        {
          "start": 93824996778861,
          "end": 93824996779029
        },
        {
          "start": 93824996779115,
          "end": 93824996779122
        },
        {
          "start": 93824996779209,
          "end": 93824996779221
        },
        {
          "start": 93824996779698,
          "end": 93824996779867
        },
        {
          "start": 93824996779933,
          "end": 93824996779996
        },
        {
          "start": 93824996819432,
          "end": 93824996819772
        },
        {
          "start": 93824996821691,
          "end": 93824996823017
        },
        {
          "start": 93824996823820,
          "end": 93824996823907
        },
        {
          "start": 93824996829368,
          "end": 93824996829402
        },
        {
          "start": 93824996829461,
          "end": 93824996829479
        },
        {
          "start": 93824996829536,
          "end": 93824996829565
        },
        {
          "start": 93824996829602,
          "end": 93824996829714
        },
        {
          "start": 93824996830352,
          "end": 93824996830460
        },
        {
          "start": 93824996830535,
          "end": 93824996830549
        },
        {
          "start": 93824996830680,
          "end": 93824996830726
        },
        {
          "start": 93824996830774,
          "end": 93824996830885
        },
        {
          "start": 93824996831711,
          "end": 93824996831729
        },
        {
          "start": 93824996831936,
          "end": 93824996832069
        },
        {
          "start": 93824996835604,
          "end": 93824996835912
        },
        {
          "start": 93824996839178,
          "end": 93824996839204
        },
        {
          "start": 93824996840135,
          "end": 93824996841681
        },
        {
          "start": 93824996841850,
          "end": 93824996841884
        },
        {
          "start": 93824996842182,
          "end": 93824996842216
        },
        {
          "start": 93824996842264,
          "end": 93824996842268
        },
        {
          "start": 93824996843560,
          "end": 93824996843620
        },
        {
          "start": 93824996843940,
          "end": 93824996844072
        },
        {
          "start": 93824996844131,
          "end": 93824996844342
        },
        {
          "start": 93824996844461,
          "end": 93824996844873
        },
        {
          "start": 93824996845398,
          "end": 93824996845534
        },
        {
          "start": 93824996845594,
          "end": 93824996845708
        },
        {
          "start": 93824996846012,
          "end": 93824996846220
        },
        {
          "start": 93824996846315,
          "end": 93824996846444
        },
        {
          "start": 93824996848613,
          "end": 93824996848682
        },
        {
          "start": 93824996848796,
          "end": 93824996848936
        },
        {
          "start": 93824996849039,
          "end": 93824996849115
        },
        {
          "start": 93824996849176,
          "end": 93824996849192
        },
        {
          "start": 93824996849282,
          "end": 93824996849523
        },
        {
          "start": 93824996849565,
          "end": 93824996849675
        },
        {
          "start": 93824996849783,
          "end": 93824996849890
        },
        {
          "start": 93824996850137,
          "end": 93824996850166
        },
        {
          "start": 93824996850882,
          "end": 93824996850919
        },
        {
          "start": 93824996851046,
          "end": 93824996851703
        },
        {
          "start": 93824996851811,
          "end": 93824996851850
        },
        {
          "start": 93824996851944,
          "end": 93824996851950
        },
        {
          "start": 93824996851987,
          "end": 93824996852073
        },
        {
          "start": 93824996852744,
          "end": 93824996853128
        },
        {
          "start": 93824996853227,
          "end": 93824996853687
        },
        {
          "start": 93824996853742,
          "end": 93824996853963
        },
        {
          "start": 93824996854331,
          "end": 93824996854416
        },
        {
          "start": 93824996855631,
          "end": 93824996856069
        },
        {
          "start": 93824996856339,
          "end": 93824996856586
        },
        {
          "start": 93824996857800,
          "end": 93824996857807
        },
        {
          "start": 93824996857996,
          "end": 93824996858016
        },
        {
          "start": 93824996858053,
          "end": 93824996858078
        },
        {
          "start": 93824996859699,
          "end": 93824996859820
        },
        {
          "start": 93824996860008,
          "end": 93824996860174
        },
        {
          "start": 93824996861194,
          "end": 93824996861270
        },
        {
          "start": 93824996862452,
          "end": 93824996862479
        },
        {
          "start": 93824998059890,
          "end": 93824998060676
        },
        {
          "start": 93824998060723,
          "end": 93824998061360
        },
        {
          "start": 93824998061395,
          "end": 93824998061429
        },
        {
          "start": 93824998061694,
          "end": 93824998061872
        },
        {
          "start": 93824998061937,
          "end": 93824998061947
        },
        {
          "start": 93824998061990,
          "end": 93824998062108
        },
        {
          "start": 93824998064634,
          "end": 93824998064648
        },
        {
          "start": 93824998064691,
          "end": 93824998064799
        },
        {
          "start": 93824998064851,
          "end": 93824998064907
        },
        {
          "start": 93824998065097,
          "end": 93824998065190
        },
        {
          "start": 93824998065867,
          "end": 93824998066094
        },
        {
          "start": 93824998066154,
          "end": 93824998066171
        },
        {
          "start": 93824998066385,
          "end": 93824998066710
        },
        {
          "start": 93824998066992,
          "end": 93824998067125
        },
        {
          "start": 93824998067579,
          "end": 93824998067648
        },
        {
          "start": 93824998067777,
          "end": 93824998067890
        },
        {
          "start": 93824998068005,
          "end": 93824998068947
        },
        {
          "start": 93824998069282,
          "end": 93824998069346
        },
        {
          "start": 93824998069426,
          "end": 93824998069539
        },
        {
          "start": 93824998069619,
          "end": 93824998069661
        },
        {
          "start": 93824998071417,
          "end": 93824998071460
        },
        {
          "start": 93824998090596,
          "end": 93824998090632
        },
        {
          "start": 93824998090955,
          "end": 93824998091054
        },
        {
          "start": 93824998091629,
          "end": 93824998091732
        },
        {
          "start": 93824998092222,
          "end": 93824998092234
        },
        {
          "start": 93824998092577,
          "end": 93824998092685
        },
        {
          "start": 93824998093223,
          "end": 93824998093261
        },
        {
          "start": 93824998093783,
          "end": 93824998093907
        },
        {
          "start": 93824998102600,
          "end": 93824998102939
        },
        {
          "start": 93824998103078,
          "end": 93824998103083
        },
        {
          "start": 93824998103144,
          "end": 93824998103305
        },
        {
          "start": 93824998119047,
          "end": 93824998119155
        },
        {
          "start": 93824998126856,
          "end": 93824998126905
        },
        {
          "start": 93824998127850,
          "end": 93824998127957
        },
        {
          "start": 93824998128051,
          "end": 93824998128089
        },
        {
          "start": 93824998128157,
          "end": 93824998128304
        },
        {
          "start": 93824998130931,
          "end": 93824998130962
        },
        {
          "start": 93824998131463,
          "end": 93824998131469
        },
        {
          "start": 93824998131518,
          "end": 93824998131544
        },
        {
          "start": 93824998131748,
          "end": 93824998132054
        },
        {
          "start": 93824998132167,
          "end": 93824998132277
        },
        {
          "start": 93824998134607,
          "end": 93824998134986
        },
        {
          "start": 93824998135062,
          "end": 93824998135350
        },
        {
          "start": 93824998152919,
          "end": 93824998153025
        },
        {
          "start": 93824998154103,
          "end": 93824998154200
        },
        {
          "start": 93824998154601,
          "end": 93824998154757
        },
        {
          "start": 93824998154971,
          "end": 93824998155312
        },
        {
          "start": 93824998155584,
          "end": 93824998155625
        },
        {
          "start": 93824998155697,
          "end": 93824998155726
        },
        {
          "start": 93824998155835,
          "end": 93824998155851
        },
        {
          "start": 93824998155893,
          "end": 93824998155910
        },
        {
          "start": 93824998157864,
          "end": 93824998157876
        },
        {
          "start": 93824998159208,
          "end": 93824998159283
        },
        {
          "start": 93824998159382,
          "end": 93824998159533
        },
        {
          "start": 93824998159850,
          "end": 93824998159888
        },
        {
          "start": 93824998159928,
          "end": 93824998159942
        },
        {
          "start": 93824998160055,
          "end": 93824998160114
        },
        {
          "start": 93824998160261,
          "end": 93824998160294
        },
        {
          "start": 93824998161179,
          "end": 93824998161202
        },
        {
          "start": 93824998161664,
          "end": 93824998161724
        },
        {
          "start": 93824998162679,
          "end": 93824998162723
        },
        {
          "start": 93824998162862,
          "end": 93824998162876
        },
        {
          "start": 93824998163152,
          "end": 93824998163205
        },
        {
          "start": 93824998165614,
          "end": 93824998165849
        },
        {
          "start": 93824998165986,
          "end": 93824998166045
        },
        {
          "start": 93824998166112,
          "end": 93824998166120
        },
        {
          "start": 93824998166672,
          "end": 93824998166694
        },
        {
          "start": 93824998166806,
          "end": 93824998167075
        },
        {
          "start": 93824998167514,
          "end": 93824998167645
        },
        {
          "start": 93824998167710,
          "end": 93824998167724
        },
        {
          "start": 93824998167853,
          "end": 93824998167881
        },
        {
          "start": 93824998168171,
          "end": 93824998168213
        },
        {
          "start": 93824998168316,
          "end": 93824998168385
        },
        {
          "start": 93824998168522,
          "end": 93824998168618
        },
        {
          "start": 93824998168719,
          "end": 93824998168727
        },
        {
          "start": 93824998168762,
          "end": 93824998168789
        },
        {
          "start": 93824998168858,
          "end": 93824998169004
        },
        {
          "start": 93824998171962,
          "end": 93824998172266
        },
        {
          "start": 93824998172330,
          "end": 93824998172465
        },
        {
          "start": 93824998172540,
          "end": 93824998172559
        },
        {
          "start": 93824998172633,
          "end": 93824998172851
        },
        {
          "start": 93824998173036,
          "end": 93824998173059
        },
        {
          "start": 93824998173125,
          "end": 93824998173129
        },
        {
          "start": 93824998173181,
          "end": 93824998173265
        },
        {
          "start": 93824998173627,
          "end": 93824998173705
        },
        {
          "start": 93824998173751,
          "end": 93824998173866
        },
        {
          "start": 93824998173964,
          "end": 93824998174136
        },
        {
          "start": 93824998174220,
          "end": 93824998174312
        },
        {
          "start": 93824998174868,
          "end": 93824998175152
        },
        {
          "start": 93824998175893,
          "end": 93824998175988
        },
        {
          "start": 93824998177544,
          "end": 93824998177571
        },
        {
          "start": 93824998182316,
          "end": 93824998182333
        },
        {
          "start": 93824998182679,
          "end": 93824998183106
        },
        {
          "start": 93824998188841,
          "end": 93824998189138
        },
        {
          "start": 93824998189264,
          "end": 93824998189321
        },
        {
          "start": 93824998197187,
          "end": 93824998197250
        },
        {
          "start": 93824998200207,
          "end": 93824998200314
        },
        {
          "start": 93824998200467,
          "end": 93824998200486
        },
        {
          "start": 93824998200551,
          "end": 93824998200794
        },
        {
          "start": 93824998202625,
          "end": 93824998202629
        },
        {
          "start": 93824998202993,
          "end": 93824998203071
        },
        {
          "start": 93824998206882,
          "end": 93824998207014
        },
        {
          "start": 93824998207059,
          "end": 93824998207333
        },
        {
          "start": 93824998207774,
          "end": 93824998208104
        },
        {
          "start": 93824998208166,
          "end": 93824998208236
        },
        {
          "start": 93824998209717,
          "end": 93824998209751
        },
        {
          "start": 93824998210036,
          "end": 93824998210055
        },
        {
          "start": 93824998210095,
          "end": 93824998210232
        },
        {
          "start": 93824998210316,
          "end": 93824998210410
        },
        {
          "start": 93824998210483,
          "end": 93824998210554
        },
        {
          "start": 93824998210587,
          "end": 93824998210618
        },
        {
          "start": 93824998210678,
          "end": 93824998210719
        },
        {
          "start": 93824998210764,
          "end": 93824998210774
        },
        {
          "start": 93824998210889,
          "end": 93824998210913
        },
        {
          "start": 93824998210957,
          "end": 93824998210981
        },
        {
          "start": 93824998211153,
          "end": 93824998211212
        },
        {
          "start": 93824998211256,
          "end": 93824998211423
        },
        {
          "start": 93824998211596,
          "end": 93824998211825
        },
        {
          "start": 93824998213164,
          "end": 93824998213287
        },
        {
          "start": 93824998218219,
          "end": 93824998218362
        },
        {
          "start": 93824998218422,
          "end": 93824998218724
        },
        {
          "start": 93824998218766,
          "end": 93824998218949
        },
        {
          "start": 93824998218986,
          "end": 93824998219661
        },
        {
          "start": 93824998219743,
          "end": 93824998219851
        },
        {
          "start": 93824998220173,
          "end": 93824998220626
        },
        {
          "start": 93824998220738,
          "end": 93824998220769
        },
        {
          "start": 93824998220988,
          "end": 93824998221150
        },
        {
          "start": 93824998221202,
          "end": 93824998221271
        },
        {
          "start": 93824998221305,
          "end": 93824998221563
        },
        {
          "start": 93824998221705,
          "end": 93824998221758
        },
        {
          "start": 93824998221895,
          "end": 93824998222119
        },
        {
          "start": 93824998222280,
          "end": 93824998222317
        },
        {
          "start": 93824998222457,
          "end": 93824998222518
        },
        {
          "start": 93824998222583,
          "end": 93824998222738
        },
        {
          "start": 93824998222818,
          "end": 93824998222861
        },
        {
          "start": 93824998222945,
          "end": 93824998223191
        },
        {
          "start": 93824998223383,
          "end": 93824998223554
        },
        {
          "start": 93824998223621,
          "end": 93824998223931
        },
        {
          "start": 93824998224047,
          "end": 93824998224080
        },
        {
          "start": 93824998225270,
          "end": 93824998228431
        },
        {
          "start": 93824998229150,
          "end": 93824998229279
        },
        {
          "start": 93824998231373,
          "end": 93824998231385
        },
        {
          "start": 93824998233000,
          "end": 93824998233024
        },
        {
          "start": 93824998233502,
          "end": 93824998233550
        },
        {
          "start": 93824998234058,
          "end": 93824998234076
        },
        {
          "start": 93824998234113,
          "end": 93824998234138
        },
        {
          "start": 93824998245222,
          "end": 93824998245290
        },
        {
          "start": 93824998245457,
          "end": 93824998245478
        },
        {
          "start": 93824998245855,
          "end": 93824998246029
        },
        {
          "start": 93824998246950,
          "end": 93824998246970
        },
        {
          "start": 93824998254429,
          "end": 93824998254569
        },
        {
          "start": 93824998263014,
          "end": 93824998263133
        },
        {
          "start": 93824998263201,
          "end": 93824998263329
        },
        {
          "start": 93824998264079,
          "end": 93824998264122
        },
        {
          "start": 93824998265201,
          "end": 93824998265358
        },
        {
          "start": 93824998265492,
          "end": 93824998265590
        },
        {
          "start": 93824998267445,
          "end": 93824998267977
        },
        {
          "start": 93824998288992,
          "end": 93824998289086
        },
        {
          "start": 93824998291791,
          "end": 93824998291829
        },
        {
          "start": 93824998291911,
          "end": 93824998292194
        },
        {
          "start": 93824998297777,
          "end": 93824998297980
        },
        {
          "start": 93824998505568,
          "end": 93824998505580
        }
      ],
      "prepared_at": "2025-12-01T18:13:32.965130"
    }
  ]
}